<?xml version="1.0" encoding="ISO-8859-1"?>
<root>
	<item id="Title"><![CDATA[Discuz! Plugin]]></item>
	<item id="Data">
		<item id="plugin">
			<item id="available"><![CDATA[1]]></item>
			<item id="adminid"><![CDATA[1]]></item>
			<item id="name"><![CDATA[Cloud Search]]></item>
			<item id="identifier"><![CDATA[cloudsearch]]></item>
			<item id="description"><![CDATA[]]></item>
			<item id="datatables"><![CDATA[]]></item>
			<item id="directory"><![CDATA[cloudsearch/]]></item>
			<item id="copyright"><![CDATA[Comsenz Inc.]]></item>
			<item id="version"><![CDATA[1.07.1]]></item>
			<item id="__modules">
				<item id="0">
					<item id="name"><![CDATA[search]]></item>
					<item id="param"><![CDATA[]]></item>
					<item id="menu"><![CDATA[]]></item>
					<item id="url"><![CDATA[]]></item>
					<item id="type"><![CDATA[11]]></item>
					<item id="adminid"><![CDATA[0]]></item>
					<item id="displayorder"><![CDATA[0]]></item>
					<item id="navtitle"><![CDATA[]]></item>
					<item id="navicon"><![CDATA[]]></item>
					<item id="navsubname"><![CDATA[]]></item>
					<item id="navsuburl"><![CDATA[]]></item>
				</item>
				<item id="1">
					<item id="name"><![CDATA[search_wap]]></item>
					<item id="param"><![CDATA[]]></item>
					<item id="menu"><![CDATA[]]></item>
					<item id="url"><![CDATA[]]></item>
					<item id="type"><![CDATA[28]]></item>
					<item id="adminid"><![CDATA[0]]></item>
					<item id="displayorder"><![CDATA[0]]></item>
					<item id="navtitle"><![CDATA[]]></item>
					<item id="navicon"><![CDATA[]]></item>
					<item id="navsubname"><![CDATA[]]></item>
					<item id="navsuburl"><![CDATA[]]></item>
				</item>
				<item id="2">
					<item id="name"><![CDATA[admincp]]></item>
					<item id="param"><![CDATA[ac=setting]]></item>
					<item id="menu"><![CDATA[]]></item>
					<item id="url"><![CDATA[]]></item>
					<item id="type"><![CDATA[3]]></item>
					<item id="adminid"><![CDATA[0]]></item>
					<item id="displayorder"><![CDATA[0]]></item>
					<item id="navtitle"><![CDATA[]]></item>
					<item id="navicon"><![CDATA[]]></item>
					<item id="navsubname"><![CDATA[]]></item>
					<item id="navsuburl"><![CDATA[]]></item>
				</item>
				<item id="3">
					<item id="name"><![CDATA[admincp]]></item>
					<item id="param"><![CDATA[ac=iwenwen]]></item>
					<item id="menu"><![CDATA[Iwenwen]]></item>
					<item id="url"><![CDATA[]]></item>
					<item id="type"><![CDATA[3]]></item>
					<item id="adminid"><![CDATA[0]]></item>
					<item id="displayorder"><![CDATA[1]]></item>
					<item id="navtitle"><![CDATA[]]></item>
					<item id="navicon"><![CDATA[]]></item>
					<item id="navsubname"><![CDATA[]]></item>
					<item id="navsuburl"><![CDATA[]]></item>
				</item>
			</item>
		</item>
		<item id="version"><![CDATA[X3.1]]></item>
		<item id="language">
			<item id="templatelang">
				<item id="hottopic"><![CDATA[Hot topics]]></item>
				<item id="realtedthread"><![CDATA[Search for Related Topics]]></item>
				<item id="forum"><![CDATA[Forum]]></item>
				<item id="addtocollection"><![CDATA[Add to Collection]]></item>
				<item id="no_content"><![CDATA[Yet no content]]></item>
				<item id="viewmore"><![CDATA[See more]]></item>
				<item id="relate"><![CDATA[Related Topics]]></item>
				<item id="orderby"><![CDATA[Order by]]></item>
				<item id="order_default"><![CDATA[Relevance]]></item>
				<item id="order_posted"><![CDATA[Post time]]></item>
				<item id="thread_class"><![CDATA[Thread Category]]></item>
				<item id="loading"><![CDATA[Loading ...]]></item>
				<item id="forumhottopic"><![CDATA[Hot Topics]]></item>
				<item id="current"><![CDATA[Edition]]></item>
			</item>
		</item>
		<item id="installfile"><![CDATA[install.php]]></item>
		<item id="upgradefile"><![CDATA[upgrade.php]]></item>
		<item id="enablefile"><![CDATA[switch.php]]></item>
		<item id="disablefile"><![CDATA[switch.php]]></item>
	</item>
</root>
